[
  {
    "ContainingType": "QuickStart.WepApi.Controllers.AboutController",
    "Method": "AboutList",
    "RelativePath": "api/About",
    "HttpMethod": "GET",
    "IsController": true,
    "Order": 0,
    "Parameters": [],
    "ReturnTypes": []
  },
  {
    "ContainingType": "QuickStart.WepApi.Controllers.AboutController",
    "Method": "CreateAbout",
    "RelativePath": "api/About",
    "HttpMethod": "POST",
    "IsController": true,
    "Order": 0,
    "Parameters": [
      {
        "Name": "about",
        "Type": "QuickStart.WepApi.Entities.About",
        "IsRequired": true
      }
    ],
    "ReturnTypes": []
  },
  {
    "ContainingType": "QuickStart.WepApi.Controllers.AboutController",
    "Method": "UpdateAbout",
    "RelativePath": "api/About",
    "HttpMethod": "PUT",
    "IsController": true,
    "Order": 0,
    "Parameters": [
      {
        "Name": "about",
        "Type": "QuickStart.WepApi.Entities.About",
        "IsRequired": true
      }
    ],
    "ReturnTypes": []
  },
  {
    "ContainingType": "QuickStart.WepApi.Controllers.AboutController",
    "Method": "DeleteAbout",
    "RelativePath": "api/About",
    "HttpMethod": "DELETE",
    "IsController": true,
    "Order": 0,
    "Parameters": [
      {
        "Name": "id",
        "Type": "System.Int32",
        "IsRequired": false
      }
    ],
    "ReturnTypes": []
  },
  {
    "ContainingType": "QuickStart.WepApi.Controllers.AboutController",
    "Method": "GetById",
    "RelativePath": "api/About/{id}",
    "HttpMethod": "GET",
    "IsController": true,
    "Order": 0,
    "Parameters": [
      {
        "Name": "id",
        "Type": "System.Int32",
        "IsRequired": true
      }
    ],
    "ReturnTypes": []
  },
  {
    "ContainingType": "QuickStart.WepApi.Controllers.AboutController",
    "Method": "AboutCount",
    "RelativePath": "api/About/AboutCount",
    "HttpMethod": "GET",
    "IsController": true,
    "Order": 0,
    "Parameters": [],
    "ReturnTypes": []
  },
  {
    "ContainingType": "QuickStart.WepApi.Controllers.ContactInfoController",
    "Method": "ContactInfoList",
    "RelativePath": "api/ContactInfo",
    "HttpMethod": "GET",
    "IsController": true,
    "Order": 0,
    "Parameters": [],
    "ReturnTypes": []
  },
  {
    "ContainingType": "QuickStart.WepApi.Controllers.ContactInfoController",
    "Method": "CreateContactInfo",
    "RelativePath": "api/ContactInfo",
    "HttpMethod": "POST",
    "IsController": true,
    "Order": 0,
    "Parameters": [
      {
        "Name": "contactInfo",
        "Type": "QuickStart.WepApi.Entities.ContactInfo",
        "IsRequired": true
      }
    ],
    "ReturnTypes": []
  },
  {
    "ContainingType": "QuickStart.WepApi.Controllers.ContactInfoController",
    "Method": "UpdateContactInfo",
    "RelativePath": "api/ContactInfo",
    "HttpMethod": "PUT",
    "IsController": true,
    "Order": 0,
    "Parameters": [
      {
        "Name": "contactInfo",
        "Type": "QuickStart.WepApi.Entities.ContactInfo",
        "IsRequired": true
      }
    ],
    "ReturnTypes": []
  },
  {
    "ContainingType": "QuickStart.WepApi.Controllers.ContactInfoController",
    "Method": "DeleteContactInfo",
    "RelativePath": "api/ContactInfo",
    "HttpMethod": "DELETE",
    "IsController": true,
    "Order": 0,
    "Parameters": [
      {
        "Name": "id",
        "Type": "System.Int32",
        "IsRequired": false
      }
    ],
    "ReturnTypes": []
  },
  {
    "ContainingType": "QuickStart.WepApi.Controllers.ContactInfoController",
    "Method": "GetById",
    "RelativePath": "api/ContactInfo/{id}",
    "HttpMethod": "GET",
    "IsController": true,
    "Order": 0,
    "Parameters": [
      {
        "Name": "id",
        "Type": "System.Int32",
        "IsRequired": true
      }
    ],
    "ReturnTypes": []
  },
  {
    "ContainingType": "QuickStart.WepApi.Controllers.ContactInfoController",
    "Method": "ContactInfoCount",
    "RelativePath": "api/ContactInfo/ContactInfoCount",
    "HttpMethod": "GET",
    "IsController": true,
    "Order": 0,
    "Parameters": [],
    "ReturnTypes": []
  },
  {
    "ContainingType": "QuickStart.WepApi.Controllers.FAQController",
    "Method": "FAQList",
    "RelativePath": "api/FAQ",
    "HttpMethod": "GET",
    "IsController": true,
    "Order": 0,
    "Parameters": [],
    "ReturnTypes": []
  },
  {
    "ContainingType": "QuickStart.WepApi.Controllers.FAQController",
    "Method": "CreateFAQ",
    "RelativePath": "api/FAQ",
    "HttpMethod": "POST",
    "IsController": true,
    "Order": 0,
    "Parameters": [
      {
        "Name": "faq",
        "Type": "QuickStart.WepApi.Entities.FAQ",
        "IsRequired": true
      }
    ],
    "ReturnTypes": []
  },
  {
    "ContainingType": "QuickStart.WepApi.Controllers.FAQController",
    "Method": "UpdateFAQ",
    "RelativePath": "api/FAQ",
    "HttpMethod": "PUT",
    "IsController": true,
    "Order": 0,
    "Parameters": [
      {
        "Name": "faq",
        "Type": "QuickStart.WepApi.Entities.FAQ",
        "IsRequired": true
      }
    ],
    "ReturnTypes": []
  },
  {
    "ContainingType": "QuickStart.WepApi.Controllers.FAQController",
    "Method": "DeleteFAQ",
    "RelativePath": "api/FAQ",
    "HttpMethod": "DELETE",
    "IsController": true,
    "Order": 0,
    "Parameters": [
      {
        "Name": "id",
        "Type": "System.Int32",
        "IsRequired": false
      }
    ],
    "ReturnTypes": []
  },
  {
    "ContainingType": "QuickStart.WepApi.Controllers.FAQController",
    "Method": "GetById",
    "RelativePath": "api/FAQ/{id}",
    "HttpMethod": "GET",
    "IsController": true,
    "Order": 0,
    "Parameters": [
      {
        "Name": "id",
        "Type": "System.Int32",
        "IsRequired": true
      }
    ],
    "ReturnTypes": []
  },
  {
    "ContainingType": "QuickStart.WepApi.Controllers.FAQController",
    "Method": "FAQCount",
    "RelativePath": "api/FAQ/FAQCount",
    "HttpMethod": "GET",
    "IsController": true,
    "Order": 0,
    "Parameters": [],
    "ReturnTypes": []
  },
  {
    "ContainingType": "QuickStart.WepApi.Controllers.FeatureController",
    "Method": "FeatureList",
    "RelativePath": "api/Feature",
    "HttpMethod": "GET",
    "IsController": true,
    "Order": 0,
    "Parameters": [],
    "ReturnTypes": []
  },
  {
    "ContainingType": "QuickStart.WepApi.Controllers.FeatureController",
    "Method": "CreateFeature",
    "RelativePath": "api/Feature",
    "HttpMethod": "POST",
    "IsController": true,
    "Order": 0,
    "Parameters": [
      {
        "Name": "feature",
        "Type": "QuickStart.WepApi.Entities.Feature",
        "IsRequired": true
      }
    ],
    "ReturnTypes": []
  },
  {
    "ContainingType": "QuickStart.WepApi.Controllers.FeatureController",
    "Method": "UpdateFeature",
    "RelativePath": "api/Feature",
    "HttpMethod": "PUT",
    "IsController": true,
    "Order": 0,
    "Parameters": [
      {
        "Name": "feature",
        "Type": "QuickStart.WepApi.Entities.Feature",
        "IsRequired": true
      }
    ],
    "ReturnTypes": []
  },
  {
    "ContainingType": "QuickStart.WepApi.Controllers.FeatureController",
    "Method": "DeleteFeature",
    "RelativePath": "api/Feature",
    "HttpMethod": "DELETE",
    "IsController": true,
    "Order": 0,
    "Parameters": [
      {
        "Name": "id",
        "Type": "System.Int32",
        "IsRequired": false
      }
    ],
    "ReturnTypes": []
  },
  {
    "ContainingType": "QuickStart.WepApi.Controllers.FeatureController",
    "Method": "GetById",
    "RelativePath": "api/Feature/{id}",
    "HttpMethod": "GET",
    "IsController": true,
    "Order": 0,
    "Parameters": [
      {
        "Name": "id",
        "Type": "System.Int32",
        "IsRequired": true
      }
    ],
    "ReturnTypes": []
  },
  {
    "ContainingType": "QuickStart.WepApi.Controllers.FeatureController",
    "Method": "FeatureCount",
    "RelativePath": "api/Feature/FeatureCount",
    "HttpMethod": "GET",
    "IsController": true,
    "Order": 0,
    "Parameters": [],
    "ReturnTypes": []
  },
  {
    "ContainingType": "QuickStart.WepApi.Controllers.MessageController",
    "Method": "MessageList",
    "RelativePath": "api/Message",
    "HttpMethod": "GET",
    "IsController": true,
    "Order": 0,
    "Parameters": [],
    "ReturnTypes": []
  },
  {
    "ContainingType": "QuickStart.WepApi.Controllers.MessageController",
    "Method": "CreateMessage",
    "RelativePath": "api/Message",
    "HttpMethod": "POST",
    "IsController": true,
    "Order": 0,
    "Parameters": [
      {
        "Name": "message",
        "Type": "QuickStart.WepApi.Entities.Message",
        "IsRequired": true
      }
    ],
    "ReturnTypes": []
  },
  {
    "ContainingType": "QuickStart.WepApi.Controllers.MessageController",
    "Method": "UpdateMessage",
    "RelativePath": "api/Message",
    "HttpMethod": "PUT",
    "IsController": true,
    "Order": 0,
    "Parameters": [
      {
        "Name": "message",
        "Type": "QuickStart.WepApi.Entities.Message",
        "IsRequired": true
      }
    ],
    "ReturnTypes": []
  },
  {
    "ContainingType": "QuickStart.WepApi.Controllers.MessageController",
    "Method": "DeleteMessage",
    "RelativePath": "api/Message",
    "HttpMethod": "DELETE",
    "IsController": true,
    "Order": 0,
    "Parameters": [
      {
        "Name": "id",
        "Type": "System.Int32",
        "IsRequired": false
      }
    ],
    "ReturnTypes": []
  },
  {
    "ContainingType": "QuickStart.WepApi.Controllers.MessageController",
    "Method": "GetById",
    "RelativePath": "api/Message/{id}",
    "HttpMethod": "GET",
    "IsController": true,
    "Order": 0,
    "Parameters": [
      {
        "Name": "id",
        "Type": "System.Int32",
        "IsRequired": true
      }
    ],
    "ReturnTypes": []
  },
  {
    "ContainingType": "QuickStart.WepApi.Controllers.MessageController",
    "Method": "MessageCount",
    "RelativePath": "api/Message/MessageCount",
    "HttpMethod": "GET",
    "IsController": true,
    "Order": 0,
    "Parameters": [],
    "ReturnTypes": []
  },
  {
    "ContainingType": "QuickStart.WepApi.Controllers.NotificationController",
    "Method": "NotificationList",
    "RelativePath": "api/Notification",
    "HttpMethod": "GET",
    "IsController": true,
    "Order": 0,
    "Parameters": [],
    "ReturnTypes": []
  },
  {
    "ContainingType": "QuickStart.WepApi.Controllers.NotificationController",
    "Method": "CreateNotification",
    "RelativePath": "api/Notification",
    "HttpMethod": "POST",
    "IsController": true,
    "Order": 0,
    "Parameters": [
      {
        "Name": "notification",
        "Type": "QuickStart.WepApi.Entity.Notification",
        "IsRequired": true
      }
    ],
    "ReturnTypes": []
  },
  {
    "ContainingType": "QuickStart.WepApi.Controllers.NotificationController",
    "Method": "UpdateNotification",
    "RelativePath": "api/Notification",
    "HttpMethod": "PUT",
    "IsController": true,
    "Order": 0,
    "Parameters": [
      {
        "Name": "notification",
        "Type": "QuickStart.WepApi.Entity.Notification",
        "IsRequired": true
      }
    ],
    "ReturnTypes": []
  },
  {
    "ContainingType": "QuickStart.WepApi.Controllers.NotificationController",
    "Method": "DeleteNotification",
    "RelativePath": "api/Notification",
    "HttpMethod": "DELETE",
    "IsController": true,
    "Order": 0,
    "Parameters": [
      {
        "Name": "id",
        "Type": "System.Int32",
        "IsRequired": false
      }
    ],
    "ReturnTypes": []
  },
  {
    "ContainingType": "QuickStart.WepApi.Controllers.NotificationController",
    "Method": "GetById",
    "RelativePath": "api/Notification/{id}",
    "HttpMethod": "GET",
    "IsController": true,
    "Order": 0,
    "Parameters": [
      {
        "Name": "id",
        "Type": "System.Int32",
        "IsRequired": true
      }
    ],
    "ReturnTypes": []
  },
  {
    "ContainingType": "QuickStart.WepApi.Controllers.NotificationController",
    "Method": "NotificationCount",
    "RelativePath": "api/Notification/NotificationCount",
    "HttpMethod": "GET",
    "IsController": true,
    "Order": 0,
    "Parameters": [],
    "ReturnTypes": []
  },
  {
    "ContainingType": "QuickStart.WepApi.Controllers.NotificationTypeController",
    "Method": "NotificationTypeList",
    "RelativePath": "api/NotificationType",
    "HttpMethod": "GET",
    "IsController": true,
    "Order": 0,
    "Parameters": [],
    "ReturnTypes": []
  },
  {
    "ContainingType": "QuickStart.WepApi.Controllers.NotificationTypeController",
    "Method": "CreateNotificationType",
    "RelativePath": "api/NotificationType",
    "HttpMethod": "POST",
    "IsController": true,
    "Order": 0,
    "Parameters": [
      {
        "Name": "notificationType",
        "Type": "QuickStart.WepApi.Entity.NotificationType",
        "IsRequired": true
      }
    ],
    "ReturnTypes": []
  },
  {
    "ContainingType": "QuickStart.WepApi.Controllers.NotificationTypeController",
    "Method": "UpdateNotificationType",
    "RelativePath": "api/NotificationType",
    "HttpMethod": "PUT",
    "IsController": true,
    "Order": 0,
    "Parameters": [
      {
        "Name": "notificationType",
        "Type": "QuickStart.WepApi.Entity.NotificationType",
        "IsRequired": true
      }
    ],
    "ReturnTypes": []
  },
  {
    "ContainingType": "QuickStart.WepApi.Controllers.NotificationTypeController",
    "Method": "DeleteNotificationType",
    "RelativePath": "api/NotificationType",
    "HttpMethod": "DELETE",
    "IsController": true,
    "Order": 0,
    "Parameters": [
      {
        "Name": "id",
        "Type": "System.Int32",
        "IsRequired": false
      }
    ],
    "ReturnTypes": []
  },
  {
    "ContainingType": "QuickStart.WepApi.Controllers.NotificationTypeController",
    "Method": "GetById",
    "RelativePath": "api/NotificationType/{id}",
    "HttpMethod": "GET",
    "IsController": true,
    "Order": 0,
    "Parameters": [
      {
        "Name": "id",
        "Type": "System.Int32",
        "IsRequired": true
      }
    ],
    "ReturnTypes": []
  },
  {
    "ContainingType": "QuickStart.WepApi.Controllers.NotificationTypeController",
    "Method": "NotificationTypeCount",
    "RelativePath": "api/NotificationType/NotificationTypeCount",
    "HttpMethod": "GET",
    "IsController": true,
    "Order": 0,
    "Parameters": [],
    "ReturnTypes": []
  },
  {
    "ContainingType": "QuickStart.WepApi.Controllers.ServiceController",
    "Method": "ServiceList",
    "RelativePath": "api/Service",
    "HttpMethod": "GET",
    "IsController": true,
    "Order": 0,
    "Parameters": [],
    "ReturnTypes": []
  },
  {
    "ContainingType": "QuickStart.WepApi.Controllers.ServiceController",
    "Method": "CreateService",
    "RelativePath": "api/Service",
    "HttpMethod": "POST",
    "IsController": true,
    "Order": 0,
    "Parameters": [
      {
        "Name": "service",
        "Type": "QuickStart.WepApi.Entity.Service",
        "IsRequired": true
      }
    ],
    "ReturnTypes": []
  },
  {
    "ContainingType": "QuickStart.WepApi.Controllers.ServiceController",
    "Method": "UpdateService",
    "RelativePath": "api/Service",
    "HttpMethod": "PUT",
    "IsController": true,
    "Order": 0,
    "Parameters": [
      {
        "Name": "service",
        "Type": "QuickStart.WepApi.Entity.Service",
        "IsRequired": true
      }
    ],
    "ReturnTypes": []
  },
  {
    "ContainingType": "QuickStart.WepApi.Controllers.ServiceController",
    "Method": "DeleteService",
    "RelativePath": "api/Service",
    "HttpMethod": "DELETE",
    "IsController": true,
    "Order": 0,
    "Parameters": [
      {
        "Name": "id",
        "Type": "System.Int32",
        "IsRequired": false
      }
    ],
    "ReturnTypes": []
  },
  {
    "ContainingType": "QuickStart.WepApi.Controllers.ServiceController",
    "Method": "GetById",
    "RelativePath": "api/Service/{id}",
    "HttpMethod": "GET",
    "IsController": true,
    "Order": 0,
    "Parameters": [
      {
        "Name": "id",
        "Type": "System.Int32",
        "IsRequired": true
      }
    ],
    "ReturnTypes": []
  },
  {
    "ContainingType": "QuickStart.WepApi.Controllers.ServiceController",
    "Method": "ServiceCount",
    "RelativePath": "api/Service/ServiceCount",
    "HttpMethod": "GET",
    "IsController": true,
    "Order": 0,
    "Parameters": [],
    "ReturnTypes": []
  },
  {
    "ContainingType": "QuickStart.WepApi.Controllers.SliderController",
    "Method": "SliderList",
    "RelativePath": "api/Slider",
    "HttpMethod": "GET",
    "IsController": true,
    "Order": 0,
    "Parameters": [],
    "ReturnTypes": []
  },
  {
    "ContainingType": "QuickStart.WepApi.Controllers.SliderController",
    "Method": "CreateSlider",
    "RelativePath": "api/Slider",
    "HttpMethod": "POST",
    "IsController": true,
    "Order": 0,
    "Parameters": [
      {
        "Name": "slider",
        "Type": "QuickStart.WepApi.Entities.Slider",
        "IsRequired": true
      }
    ],
    "ReturnTypes": []
  },
  {
    "ContainingType": "QuickStart.WepApi.Controllers.SliderController",
    "Method": "UpdateSlider",
    "RelativePath": "api/Slider",
    "HttpMethod": "PUT",
    "IsController": true,
    "Order": 0,
    "Parameters": [
      {
        "Name": "slider",
        "Type": "QuickStart.WepApi.Entities.Slider",
        "IsRequired": true
      }
    ],
    "ReturnTypes": []
  },
  {
    "ContainingType": "QuickStart.WepApi.Controllers.SliderController",
    "Method": "DeleteSlider",
    "RelativePath": "api/Slider",
    "HttpMethod": "DELETE",
    "IsController": true,
    "Order": 0,
    "Parameters": [
      {
        "Name": "id",
        "Type": "System.Int32",
        "IsRequired": false
      }
    ],
    "ReturnTypes": []
  },
  {
    "ContainingType": "QuickStart.WepApi.Controllers.SliderController",
    "Method": "GetById",
    "RelativePath": "api/Slider/{id}",
    "HttpMethod": "GET",
    "IsController": true,
    "Order": 0,
    "Parameters": [
      {
        "Name": "id",
        "Type": "System.Int32",
        "IsRequired": true
      }
    ],
    "ReturnTypes": []
  },
  {
    "ContainingType": "QuickStart.WepApi.Controllers.SliderController",
    "Method": "SliderCount",
    "RelativePath": "api/Slider/SliderCount",
    "HttpMethod": "GET",
    "IsController": true,
    "Order": 0,
    "Parameters": [],
    "ReturnTypes": []
  },
  {
    "ContainingType": "QuickStart.WepApi.Controllers.TestimonialController",
    "Method": "TestimonialList",
    "RelativePath": "api/Testimonial",
    "HttpMethod": "GET",
    "IsController": true,
    "Order": 0,
    "Parameters": [],
    "ReturnTypes": []
  },
  {
    "ContainingType": "QuickStart.WepApi.Controllers.TestimonialController",
    "Method": "CreateTestimonial",
    "RelativePath": "api/Testimonial",
    "HttpMethod": "POST",
    "IsController": true,
    "Order": 0,
    "Parameters": [
      {
        "Name": "testimonial",
        "Type": "QuickStart.WepApi.Entity.Testimonial",
        "IsRequired": true
      }
    ],
    "ReturnTypes": []
  },
  {
    "ContainingType": "QuickStart.WepApi.Controllers.TestimonialController",
    "Method": "UpdateTestimonial",
    "RelativePath": "api/Testimonial",
    "HttpMethod": "PUT",
    "IsController": true,
    "Order": 0,
    "Parameters": [
      {
        "Name": "testimonial",
        "Type": "QuickStart.WepApi.Entity.Testimonial",
        "IsRequired": true
      }
    ],
    "ReturnTypes": []
  },
  {
    "ContainingType": "QuickStart.WepApi.Controllers.TestimonialController",
    "Method": "DeleteTestimonial",
    "RelativePath": "api/Testimonial",
    "HttpMethod": "DELETE",
    "IsController": true,
    "Order": 0,
    "Parameters": [
      {
        "Name": "id",
        "Type": "System.Int32",
        "IsRequired": false
      }
    ],
    "ReturnTypes": []
  },
  {
    "ContainingType": "QuickStart.WepApi.Controllers.TestimonialController",
    "Method": "GetById",
    "RelativePath": "api/Testimonial/{id}",
    "HttpMethod": "GET",
    "IsController": true,
    "Order": 0,
    "Parameters": [
      {
        "Name": "id",
        "Type": "System.Int32",
        "IsRequired": true
      }
    ],
    "ReturnTypes": []
  },
  {
    "ContainingType": "QuickStart.WepApi.Controllers.TestimonialController",
    "Method": "TestimonialCount",
    "RelativePath": "api/Testimonial/TestimonialCount",
    "HttpMethod": "GET",
    "IsController": true,
    "Order": 0,
    "Parameters": [],
    "ReturnTypes": []
  },
  {
    "ContainingType": "QuickStart.WepApi.Controllers.WeatherForecastController",
    "Method": "Get",
    "RelativePath": "WeatherForecast",
    "HttpMethod": "GET",
    "IsController": true,
    "Order": 0,
    "Parameters": [],
    "ReturnTypes": [
      {
        "Type": "System.Collections.Generic.IEnumerable\u00601[[QuickStart.WepApi.WeatherForecast, QuickStart.WepApi, Version=1.0.0.0, Culture=neutral, PublicKeyToken=null]]",
        "MediaTypes": [
          "text/plain",
          "application/json",
          "text/json"
        ],
        "StatusCode": 200
      }
    ],
    "EndpointName": "GetWeatherForecast"
  }
]